djecorator.py
djecorator-1.2.0.dist-info/licenses/LICENSE
djecorator-1.2.0.dist-info/WHEEL
djecorator-1.2.0.dist-info/METADATA
djecorator-1.2.0.dist-info/RECORD
