Metadata-Version: 2.4
Name: djecorator
Version: 1.2.0
Summary: A flask-style decorator for Django views
Author-email: Stephan Fitzpatrick <knowsuchagency@gmail.com>
Classifier: License :: OSI Approved :: MIT License
License-File: LICENSE
Requires-Dist: django
Project-URL: Source, https://github.com/knowsuchagency/djecorator
